LICENSE
README.md
setup.py
ztfimg/__init__.py
ztfimg/base.py
ztfimg/catalog.py
ztfimg/collection.py
ztfimg/io.py
ztfimg/raw.py
ztfimg/science.py
ztfimg.egg-info/PKG-INFO
ztfimg.egg-info/SOURCES.txt
ztfimg.egg-info/dependency_links.txt
ztfimg.egg-info/top_level.txt
ztfimg/data/ccd_amp_coeff_v2.txt
ztfimg/data/ztf_20200924431759_000655_zr_c13_o_q3_mskimg.fits
ztfimg/data/ztf_20200924431759_000655_zr_c13_o_q3_sciimg.fits
ztfimg/utils/__init__.py
ztfimg/utils/astrometry.py
ztfimg/utils/decorators.py
ztfimg/utils/tools.py