Metadata-Version: 2.1
Name: ztfimg
Version: 0.16.0
Summary:  ZTFimg 
Home-page: https://github.com/MickaelRigault/ztfimg
Download-URL: https://github.com/MickaelRigault/ztfimg
Author: Mickael Rigault
Author-email: m.rigault@ipnl.in2p3.fr
Maintainer: Mickael Rigault
Maintainer-email: m.rigault@ipnl.in2p3.fr
License: BSD (3-clause)
Classifier: Intended Audience :: Science/Research
Classifier: Programming Language :: Python :: 3.6
Classifier: License :: OSI Approved :: BSD License
Classifier: Topic :: Scientific/Engineering :: Astronomy
Classifier: Operating System :: POSIX
Classifier: Operating System :: Unix
Classifier: Operating System :: MacOS
License-File: LICENSE
